verilogae/__init__.py
verilogae/verilogae.cpython-311-x86_64-linux-gnu.so
verilogae-1.0.0.dist-info/LICENSE
verilogae-1.0.0.dist-info/METADATA
verilogae-1.0.0.dist-info/WHEEL
verilogae-1.0.0.dist-info/top_level.txt
verilogae-1.0.0.dist-info/RECORD
